src/ALU/ALU_Display.v
module ALU_Display(
    input [31:0] F,
    input ZF,
    input OF,
    input [2:0] F_LED_SW,
    output reg [7:0] LED
    );

always @(*) begin
    case (F_LED_SW)
        3'b000: LED = F[7:0];
        3'b001: LED = F[15:8];
        3'b010: LED = F[23:16];
        3'b011: LED = F[31:24];
        default: begin
            LED[7] = ZF;
            LED[0] = OF;
            LED[6:1] = 6'b0;
        end
    endcase
end

endmodule

src/ALU/ALU.v
module ALU(
 input [31:0]ALU_A,
 input [31:0]ALU_B,
 input [2:0]ALU_OP,
 output reg [31:0]ALU_F,
 output ZF,
 output OF
    );

always@(*)begin
 case(ALU_OP)
 3'b000:ALU_F=ALU_A&ALU_B;//and
 3'b001:ALU_F=ALU_A|ALU_B;//or
 3'b010:ALU_F=ALU_A^ALU_B;//xor
 3'b011:ALU_F=~(ALU_A|ALU_B);//nor
 3'b100:ALU_F=ALU_A+ALU_B;//add
 3'b101:ALU_F=ALU_A-ALU_B;//sub
 3'b110:ALU_F=$signed(ALU_A)<$signed(ALU_B)?1:0;//slt
 3'b111:ALU_F=ALU_A<<ALU_B[4:0];//sll using lower 5 bits
 default:ALU_F=32'b0;//default
 endcase
end

assign ZF = ~(|ALU_F);
wire add_overflow;
wire sub_overflow;
assign add_overflow = (~(ALU_A[31]^ALU_B[31])) & (ALU_A[31]^ALU_F[31]);
assign sub_overflow = (ALU_A[31]^ALU_B[31]) & (ALU_A[31]^ALU_F[31]);
assign OF = (ALU_OP==3'b100) ? add_overflow :
            (ALU_OP==3'b101) ? sub_overflow : 1'b0;

endmodule

src/ALU/ALU_Top.v
module ALU_Top (
    input [2:0] AB_SW,
    input [2:0] ALU_OP_SW,
    input [2:0] F_LED_SW,
    output reg [31:0] A,
    output reg [31:0] B,
    output [31:0] F,
    output [7:0] LED,
    output ZF,
    output OF
);

always @(*)
begin
    case (AB_SW)
        3'b000: begin A = 32'h0000_0000; B = 32'h0000_0000; end
        3'b001: begin A = 32'h0000_0003; B = 32'h0000_0607; end
        3'b010: begin A = 32'h8000_0000; B = 32'h8000_0000; end
        3'b011: begin A = 32'h7FFF_FFFF; B = 32'h7FFF_FFFF; end
        3'b100: begin A = 32'hFFFF_FFFF; B = 32'hFFFF_FFFF; end
        3'b101: begin A = 32'h8000_0000; B = 32'hFFFF_FFFF; end
        3'b110: begin A = 32'hFFFF_FFFF; B = 32'h8000_0000; end
        3'b111: begin A = 32'h1234_5678; B = 32'h3333_2222; end
        default: begin A = 32'h9ABC_DEF0; B = 32'h1111_2222; end
    endcase
end

ALU u_alu(
    .ALU_A(A),
    .ALU_B(B),
    .ALU_OP(ALU_OP_SW),
    .ALU_F(F),
    .ZF(ZF),
    .OF(OF)
);

ALU_Display u_display(
    .F(F),
    .ZF(ZF),
    .OF(OF),
    .F_LED_SW(F_LED_SW),
    .LED(LED)
);

endmodule

src/ALU/tb_ALU_Top.v
`timescale 1ns/1ps

module tb_ALU_Top;

reg [2:0] AB_SW;
reg [2:0] ALU_OP_SW;
reg [2:0] F_LED_SW;

wire [31:0] A;
wire [31:0] B;
wire [31:0] F;
wire [7:0] LED;
wire ZF;
wire OF;

integer ab_idx;
integer op_idx;

ALU_Top dut (
    .AB_SW(AB_SW),
    .ALU_OP_SW(ALU_OP_SW),
    .F_LED_SW(F_LED_SW),
    .A(A),
    .B(B),
    .F(F),
    .LED(LED),
    .ZF(ZF),
    .OF(OF)
);

localparam integer STEP_NS = 20;

initial begin
    $dumpfile("sim/alu_top_tb.vcd");
    $dumpvars(0, tb_ALU_Top);

    AB_SW = 3'b000;
    ALU_OP_SW = 3'b000;
    F_LED_SW = 3'b000;
    #STEP_NS;

    for (ab_idx = 0; ab_idx < 8; ab_idx = ab_idx + 1) begin
        AB_SW = ab_idx[2:0];
        #STEP_NS; // allow AB selection to settle
        for (op_idx = 0; op_idx < 8; op_idx = op_idx + 1) begin
            ALU_OP_SW = op_idx[2:0];
            #STEP_NS;
        end
        #STEP_NS; // hold last result before moving to next operand pair
    end

    F_LED_SW = 3'b011;
    #(2*STEP_NS);
    F_LED_SW = 3'b111; // show flags on LED
    #(2*STEP_NS);
    $finish;
end

endmodule

sim/alu_top_tb.vcd
$date
	Mon Nov 10 19:30:17 2025
$end
$version
	Icarus Verilog
$end
$timescale
	1ps
$end
$scope module tb_ALU_Top $end
$var wire 1 ! ZF $end
$var wire 1 " OF $end
$var wire 8 # LED [7:0] $end
$var wire 32 $ F [31:0] $end
$var wire 32 % B [31:0] $end
$var wire 32 & A [31:0] $end
$var parameter 32 ' STEP_NS $end
$var reg 3 ( AB_SW [2:0] $end
$var reg 3 ) ALU_OP_SW [2:0] $end
$var reg 3 * F_LED_SW [2:0] $end
$var integer 32 + ab_idx [31:0] $end
$var integer 32 , op_idx [31:0] $end
$scope module dut $end
$var wire 3 - AB_SW [2:0] $end
$var wire 3 . ALU_OP_SW [2:0] $end
$var wire 3 / F_LED_SW [2:0] $end
$var wire 1 ! ZF $end
$var wire 1 " OF $end
$var wire 8 0 LED [7:0] $end
$var wire 32 1 F [31:0] $end
$var reg 32 2 A [31:0] $end
$var reg 32 3 B [31:0] $end
$scope module u_alu $end
$var wire 32 4 ALU_A [31:0] $end
$var wire 32 5 ALU_B [31:0] $end
$var wire 3 6 ALU_OP [2:0] $end
$var wire 1 ! ZF $end
$var wire 1 7 add_overflow $end
$var wire 1 8 sub_overflow $end
$var wire 1 " OF $end
$var reg 32 9 ALU_F [31:0] $end
$upscope $end
$scope module u_display $end
$var wire 32 : F [31:0] $end
$var wire 3 ; F_LED_SW [2:0] $end
$var wire 1 " OF $end
$var wire 1 ! ZF $end
$var reg 8 < LED [7:0] $end
$upscope $end
$upscope $end
$upscope $end
$enddefinitions $end
$comment Show the parameter values. $end
$dumpall
b10100 '
$end
#0
$dumpvars
b0 <
b0 ;
b0 :
b0 9
08
07
b0 6
b0 5
b0 4
b0 3
b0 2
b0 1
b0 0
b0 /
b0 .
b0 -
bx ,
bx +
b0 *
b0 )
b0 (
b0 &
b0 %
b0 $
b0 #
0"
1!
$end
#20000
b0 +
#40000
b0 ,
#60000
b1 )
b1 .
b1 6
b1 ,
#80000
b10 )
b10 .
b10 6
b10 ,
#100000
17
0!
b11111111 #
b11111111 0
b11111111 <
b11111111111111111111111111111111 $
b11111111111111111111111111111111 1
b11111111111111111111111111111111 9
b11111111111111111111111111111111 :
b11 )
b11 .
b11 6
b11 ,
#120000
07
1!
b0 #
b0 0
b0 <
b0 $
b0 1
b0 9
b0 :
0"
b100 )
b100 .
b100 6
b100 ,
#140000
b101 )
b101 .
b101 6
b101 ,
#160000
b110 )
b110 .
b110 6
b110 ,
#180000
b111 )
b111 .
b111 6
b111 ,
#200000
b1000 ,
#220000
0!
b10000000 #
b10000000 0
b10000000 <
b110000000 $
b110000000 1
b110000000 9
b110000000 :
b11000000111 %
b11000000111 3
b11000000111 5
b11 &
b11 2
b11 4
b1 (
b1 -
b1 +
#240000
b11 #
b11 0
b11 <
b11 $
b11 1
b11 9
b11 :
b0 )
b0 .
b0 6
b0 ,
#260000
b111 #
b111 0
b111 <
b11000000111 $
b11000000111 1
b11000000111 9
b11000000111 :
b1 )
b1 .
b1 6
b1 ,
#280000
b100 #
b100 0
b100 <
b11000000100 $
b11000000100 1
b11000000100 9
b11000000100 :
b10 )
b10 .
b10 6
b10 ,
#300000
17
b11111000 #
b11111000 0
b11111000 <
b11111111111111111111100111111000 $
b11111111111111111111100111111000 1
b11111111111111111111100111111000 9
b11111111111111111111100111111000 :
b11 )
b11 .
b11 6
b11 ,
#320000
07
b1010 #
b1010 0
b1010 <
b11000001010 $
b11000001010 1
b11000001010 9
b11000001010 :
0"
b100 )
b100 .
b100 6
b100 ,
#340000
17
b11111100 #
b11111100 0
b11111100 <
b11111111111111111111100111111100 $
b11111111111111111111100111111100 1
b11111111111111111111100111111100 9
b11111111111111111111100111111100 :
b101 )
b101 .
b101 6
b101 ,
#360000
07
b1 #
b1 0
b1 <
b1 $
b1 1
b1 9
b1 :
b110 )
b110 .
b110 6
b110 ,
#380000
b10000000 #
b10000000 0
b10000000 <
b110000000 $
b110000000 1
b110000000 9
b110000000 :
b111 )
b111 .
b111 6
b111 ,
#400000
b1000 ,
#420000
07
b0 #
b0 0
b0 <
b10000000000000000000000000000000 $
b10000000000000000000000000000000 1
b10000000000000000000000000000000 9
b10000000000000000000000000000000 :
b10000000000000000000000000000000 %
b10000000000000000000000000000000 3
b10000000000000000000000000000000 5
b10000000000000000000000000000000 &
b10000000000000000000000000000000 2
b10000000000000000000000000000000 4
b10 (
b10 -
b10 +
#440000
b0 )
b0 .
b0 6
b0 ,
#460000
b1 )
b1 .
b1 6
b1 ,
#480000
17
1!
b0 $
b0 1
b0 9
b0 :
b10 )
b10 .
b10 6
b10 ,
#500000
0!
b11111111 #
b11111111 0
b11111111 <
b1111111111111111111111111111111 $
b1111111111111111111111111111111 1
b1111111111111111111111111111111 9
b1111111111111111111111111111111 :
b11 )
b11 .
b11 6
b11 ,
#520000
1!
b0 #
b0 0
b0 <
b0 $
b0 1
b0 9
b0 :
1"
b100 )
b100 .
b100 6
b100 ,
#540000
0"
b101 )
b101 .
b101 6
b101 ,
#560000
b110 )
b110 .
b110 6
b110 ,
#580000
07
0!
b10000000000000000000000000000000 $
b10000000000000000000000000000000 1
b10000000000000000000000000000000 9
b10000000000000000000000000000000 :
b111 )
b111 .
b111 6
b111 ,
#600000
b1000 ,
#620000
17
b1111111111111111111111111111111 %
b1111111111111111111111111111111 3
b1111111111111111111111111111111 5
b1111111111111111111111111111111 &
b1111111111111111111111111111111 2
b1111111111111111111111111111111 4
b11 (
b11 -
b11 +
#640000
07
b11111111 #
b11111111 0
b11111111 <
b1111111111111111111111111111111 $
b1111111111111111111111111111111 1
b1111111111111111111111111111111 9
b1111111111111111111111111111111 :
b0 )
b0 .
b0 6
b0 ,
#660000
b1 )
b1 .
b1 6
b1 ,
#680000
1!
b0 #
b0 0
b0 <
b0 $
b0 1
b0 9
b0 :
b10 )
b10 .
b10 6
b10 ,
#700000
17
0!
b10000000000000000000000000000000 $
b10000000000000000000000000000000 1
b10000000000000000000000000000000 9
b10000000000000000000000000000000 :
b11 )
b11 .
b11 6
b11 ,
#720000
b11111110 #
b11111110 0
b11111110 <
b11111111111111111111111111111110 $
b11111111111111111111111111111110 1
b11111111111111111111111111111110 9
b11111111111111111111111111111110 :
1"
b100 )
b100 .
b100 6
b100 ,
#740000
07
1!
b0 #
b0 0
b0 <
b0 $
b0 1
b0 9
b0 :
0"
b101 )
b101 .
b101 6
b101 ,
#760000
b110 )
b110 .
b110 6
b110 ,
#780000
17
0!
b10000000000000000000000000000000 $
b10000000000000000000000000000000 1
b10000000000000000000000000000000 9
b10000000000000000000000000000000 :
b111 )
b111 .
b111 6
b111 ,
#800000
b1000 ,
#820000
07
b11111111111111111111111111111111 %
b11111111111111111111111111111111 3
b11111111111111111111111111111111 5
b11111111111111111111111111111111 &
b11111111111111111111111111111111 2
b11111111111111111111111111111111 4
b100 (
b100 -
b100 +
#840000
b11111111 #
b11111111 0
b11111111 <
b11111111111111111111111111111111 $
b11111111111111111111111111111111 1
b11111111111111111111111111111111 9
b11111111111111111111111111111111 :
b0 )
b0 .
b0 6
b0 ,
#860000
b1 )
b1 .
b1 6
b1 ,
#880000
17
1!
b0 #
b0 0
b0 <
b0 $
b0 1
b0 9
b0 :
b10 )
b10 .
b10 6
b10 ,
#900000
b11 )
b11 .
b11 6
b11 ,
#920000
07
0!
b11111110 #
b11111110 0
b11111110 <
b11111111111111111111111111111110 $
b11111111111111111111111111111110 1
b11111111111111111111111111111110 9
b11111111111111111111111111111110 :
0"
b100 )
b100 .
b100 6
b100 ,
#940000
17
1!
b0 #
b0 0
b0 <
b0 $
b0 1
b0 9
b0 :
b101 )
b101 .
b101 6
b101 ,
#960000
b110 )
b110 .
b110 6
b110 ,
#980000
07
0!
b10000000000000000000000000000000 $
b10000000000000000000000000000000 1
b10000000000000000000000000000000 9
b10000000000000000000000000000000 :
b111 )
b111 .
b111 6
b111 ,
#1000000
b1000 ,
#1020000
17
1!
b0 $
b0 1
b0 9
b0 :
b10000000000000000000000000000000 &
b10000000000000000000000000000000 2
b10000000000000000000000000000000 4
b101 (
b101 -
b101 +
#1040000
07
0!
b10000000000000000000000000000000 $
b10000000000000000000000000000000 1
b10000000000000000000000000000000 9
b10000000000000000000000000000000 :
b0 )
b0 .
b0 6
b0 ,
#1060000
b11111111 #
b11111111 0
b11111111 <
b11111111111111111111111111111111 $
b11111111111111111111111111111111 1
b11111111111111111111111111111111 9
b11111111111111111111111111111111 :
b1 )
b1 .
b1 6
b1 ,
#1080000
17
b1111111111111111111111111111111 $
b1111111111111111111111111111111 1
b1111111111111111111111111111111 9
b1111111111111111111111111111111 :
b10 )
b10 .
b10 6
b10 ,
#1100000
1!
b0 #
b0 0
b0 <
b0 $
b0 1
b0 9
b0 :
b11 )
b11 .
b11 6
b11 ,
#1120000
0!
b11111111 #
b11111111 0
b11111111 <
b1111111111111111111111111111111 $
b1111111111111111111111111111111 1
b1111111111111111111111111111111 9
b1111111111111111111111111111111 :
1"
b100 )
b100 .
b100 6
b100 ,
#1140000
07
b1 #
b1 0
b1 <
b10000000000000000000000000000001 $
b10000000000000000000000000000001 1
b10000000000000000000000000000001 9
b10000000000000000000000000000001 :
0"
b101 )
b101 .
b101 6
b101 ,
#1160000
17
b1 $
b1 1
b1 9
b1 :
b110 )
b110 .
b110 6
b110 ,
#1180000
1!
b0 #
b0 0
b0 <
b0 $
b0 1
b0 9
b0 :
b111 )
b111 .
b111 6
b111 ,
#1200000
b1000 ,
#1220000
07
0!
b11111111 #
b11111111 0
b11111111 <
b11111111111111111111111111111111 $
b11111111111111111111111111111111 1
b11111111111111111111111111111111 9
b11111111111111111111111111111111 :
b10000000000000000000000000000000 %
b10000000000000000000000000000000 3
b10000000000000000000000000000000 5
b11111111111111111111111111111111 &
b11111111111111111111111111111111 2
b11111111111111111111111111111111 4
b110 (
b110 -
b110 +
#1240000
b0 #
b0 0
b0 <
b10000000000000000000000000000000 $
b10000000000000000000000000000000 1
b10000000000000000000000000000000 9
b10000000000000000000000000000000 :
b0 )
b0 .
b0 6
b0 ,
#1260000
b11111111 #
b11111111 0
b11111111 <
b11111111111111111111111111111111 $
b11111111111111111111111111111111 1
b11111111111111111111111111111111 9
b11111111111111111111111111111111 :
b1 )
b1 .
b1 6
b1 ,
#1280000
17
b1111111111111111111111111111111 $
b1111111111111111111111111111111 1
b1111111111111111111111111111111 9
b1111111111111111111111111111111 :
b10 )
b10 .
b10 6
b10 ,
#1300000
1!
b0 #
b0 0
b0 <
b0 $
b0 1
b0 9
b0 :
b11 )
b11 .
b11 6
b11 ,
#1320000
0!
b11111111 #
b11111111 0
b11111111 <
b1111111111111111111111111111111 $
b1111111111111111111111111111111 1
b1111111111111111111111111111111 9
b1111111111111111111111111111111 :
1"
b100 )
b100 .
b100 6
b100 ,
#1340000
0"
b101 )
b101 .
b101 6
b101 ,
#1360000
1!
b0 #
b0 0
b0 <
b0 $
b0 1
b0 9
b0 :
b110 )
b110 .
b110 6
b110 ,
#1380000
07
0!
b11111111 #
b11111111 0
b11111111 <
b11111111111111111111111111111111 $
b11111111111111111111111111111111 1
b11111111111111111111111111111111 9
b11111111111111111111111111111111 :
b111 )
b111 .
b111 6
b111 ,
#1400000
b1000 ,
#1420000
07
b11100000 #
b11100000 0
b11100000 <
b1001000110100010101100111100000 $
b1001000110100010101100111100000 1
b1001000110100010101100111100000 9
b1001000110100010101100111100000 :
b110011001100110010001000100010 %
b110011001100110010001000100010 3
b110011001100110010001000100010 5
b10010001101000101011001111000 &
b10010001101000101011001111000 2
b10010001101000101011001111000 4
b111 (
b111 -
b111 +
#1440000
b100000 #
b100000 0
b100000 <
b10010001100000000001000100000 $
b10010001100000000001000100000 1
b10010001100000000001000100000 9
b10010001100000000001000100000 :
b0 )
b0 .
b0 6
b0 ,
#1460000
b1111010 #
b1111010 0
b1111010 <
b110011001101110111011001111010 $
b110011001101110111011001111010 1
b110011001101110111011001111010 9
b110011001101110111011001111010 :
b1 )
b1 .
b1 6
b1 ,
#1480000
b1011010 #
b1011010 0
b1011010 <
b100001000001110111010001011010 $
b100001000001110111010001011010 1
b100001000001110111010001011010 9
b100001000001110111010001011010 :
b10 )
b10 .
b10 6
b10 ,
#1500000
17
b10000101 #
b10000101 0
b10000101 <
b11001100110010001000100110000101 $
b11001100110010001000100110000101 1
b11001100110010001000100110000101 9
b11001100110010001000100110000101 :
b11 )
b11 .
b11 6
b11 ,
#1520000
07
b10011010 #
b10011010 0
b10011010 <
b1000101011001110111100010011010 $
b1000101011001110111100010011010 1
b1000101011001110111100010011010 9
b1000101011001110111100010011010 :
0"
b100 )
b100 .
b100 6
b100 ,
#1540000
17
b1010110 #
b1010110 0
b1010110 <
b11011111000000010011010001010110 $
b11011111000000010011010001010110 1
b11011111000000010011010001010110 9
b11011111000000010011010001010110 :
b101 )
b101 .
b101 6
b101 ,
#1560000
07
b1 #
b1 0
b1 <
b1 $
b1 1
b1 9
b1 :
b110 )
b110 .
b110 6
b110 ,
#1580000
b11100000 #
b11100000 0
b11100000 <
b1001000110100010101100111100000 $
b1001000110100010101100111100000 1
b1001000110100010101100111100000 9
b1001000110100010101100111100000 :
b111 )
b111 .
b111 6
b111 ,
#1600000
b1000 ,
#1620000
b1001000 #
b1001000 0
b1001000 <
b11 *
b11 /
b11 ;
b1000 +
#1660000
b0 #
b0 0
b0 <
b111 *
b111 /
b111 ;
