src/REG/REG.v
module Reg(
    R_Addr_A, R_Addr_B, Write_Reg,
    R_Data_A, R_Data_B,
    W_Addr, W_Data,
    Reset, Clk
);

input [4:0] R_Addr_A, R_Addr_B, W_Addr;
input Write_Reg,Reset,Clk;
input[31:0] W_Data;

output [31:0] R_Data_A,R_Data_B;

reg [31:0] REG_Files[0:31];
integer i=0;

always @ (posedge Clk or posedge Reset)
	begin
		if(Reset)
			begin
				for(i=0;i<=31;i=i+1)
					REG_Files[i]<=0;
			end
		else
			begin
				if(Write_Reg)
					REG_Files[W_Addr]<=W_Data;
			end
	end
	assign R_Data_A = REG_Files[R_Addr_A];
	assign R_Data_B = REG_Files[R_Addr_B];
	
endmodule

src/REG/REG_Top.v
module Reg_Top(Addr,Write_Reg,Opt,Clk,Reset,A_B,LED);
input [1:0]Opt;
input [4:0]Addr;
input Write_Reg,Clk,Reset,A_B;
output reg [7:0]LED;
wire [31:0]R_Data_A,R_Data_B;
reg [4:0]R_Addr_A,R_Addr_B;
reg [31:0]W_Data;

initial
	LED <= 0;

Reg Reg_one(R_Addr_A,R_Addr_B,Write_Reg,R_Data_A,R_Data_B,Reset,Clk,Addr,W_Data);

always @ (Addr or Write_Reg or Opt or A_B or R_Data_A or R_Data_B)
	begin
		if(Write_Reg)
			begin
				case(Opt)
					2'b00: begin W_Data=32'h000f_000f;  end
					2'b01: begin W_Data=32'h0f0f_0f00;  end
					2'b10: begin W_Data=32'hf0f0_f0f0;  end 
					2'b11: begin W_Data=32'hffff_ffff;  end
				endcase
			end
		else
			if(A_B)
				begin
					R_Addr_A=Addr;
					case(Opt)
						2'b00: LED=R_Data_A[7:0];
						2'b01: LED=R_Data_A[15:8];
						2'b10: LED=R_Data_A[23:16];
						2'b11: LED=R_Data_A[31:24];
					endcase
				end
			else
				begin
					R_Addr_B=Addr;
					case(Opt)
						2'b00: LED=R_Data_B[7:0];
						2'b01: LED=R_Data_B[15:8];
						2'b10: LED=R_Data_B[23:16];
						2'b11: LED=R_Data_B[31:24];
					endcase
				end
	end
endmodule

src/REG/REG_Test.v
`timescale 1ns/1ps

module Reg_test;
	// Inputs
	reg [4:0] Addr;
	reg Write_Reg;
	reg [1:0] Opt;
	reg Clk;
	reg Reset;
	reg A_B;
	// Outputs
	wire [7:0] LED;

	Reg_Top uut (
		.Addr(Addr), 
		.Write_Reg(Write_Reg), 
		.Opt(Opt), 
		.Clk(Clk), 
		.Reset(Reset), 
		.A_B(A_B), 
		.LED(LED)
	);

    // 25 MHz clock
	always #20 Clk = ~Clk;

	initial begin
		$dumpfile("sim/reg_top_tb.vcd");
		$dumpvars(0, Reg_test);

		// reset
		Clk = 0;
		Reset = 1;
		Write_Reg = 0;
		Opt = 0;
		Addr = 5'b00001;
		A_B = 0;
		#50;

		// write
		Reset = 0;
		Write_Reg = 1;
		Opt = 0;
		Addr = 5'b00001;
		#80;

		// read
		Write_Reg = 0;
		A_B = 0;
		Opt = 0;
		Addr = 5'b00001;
		#100;

		$finish;
	end
endmodule

sim/reg_top_tb.vcd
$date
	Mon Dec 15 18:34:54 2025
$end
$version
	Icarus Verilog
$end
$timescale
	1ps
$end
$scope module Reg_test $end
$var wire 8 ! LED [7:0] $end
$var reg 1 " A_B $end
$var reg 5 # Addr [4:0] $end
$var reg 1 $ Clk $end
$var reg 2 % Opt [1:0] $end
$var reg 1 & Reset $end
$var reg 1 ' Write_Reg $end
$scope module uut $end
$var wire 1 " A_B $end
$var wire 5 ( Addr [4:0] $end
$var wire 1 $ Clk $end
$var wire 2 ) Opt [1:0] $end
$var wire 1 & Reset $end
$var wire 1 ' Write_Reg $end
$var wire 32 * R_Data_B [31:0] $end
$var wire 32 + R_Data_A [31:0] $end
$var reg 8 , LED [7:0] $end
$var reg 5 - R_Addr_A [4:0] $end
$var reg 5 . R_Addr_B [4:0] $end
$var reg 32 / W_Data [31:0] $end
$scope module Reg_one $end
$var wire 1 0 Clk $end
$var wire 5 1 R_Addr_A [4:0] $end
$var wire 5 2 R_Addr_B [4:0] $end
$var wire 32 3 R_Data_A [31:0] $end
$var wire 32 4 R_Data_B [31:0] $end
$var wire 1 5 Reset $end
$var wire 5 6 W_Addr [4:0] $end
$var wire 32 7 W_Data [31:0] $end
$var wire 1 ' Write_Reg $end
$var integer 32 8 i [31:0] $end
$upscope $end
$upscope $end
$upscope $end
$enddefinitions $end
$comment Show the parameter values. $end
$dumpall
$end
#0
$dumpvars
b100000 8
b0 7
b1 6
15
b0 4
bx 3
b1 2
bx 1
x0
bx /
b1 .
bx -
b0 ,
bx +
b0 *
b0 )
b1 (
0'
1&
b0 %
0$
b1 #
0"
b0 !
$end
#20000
b1 7
1$
#40000
b0 7
0$
#50000
b100000 8
10
b11110000000000001111 /
1'
b0 6
0&
#60000
b1 7
1$
#80000
b0 7
0$
#100000
b1 7
1$
#120000
b0 7
0$
#130000
0'
#140000
b1 7
1$
#160000
b0 7
0$
#180000
b1 7
1$
#200000
b0 7
0$
#220000
b1 7
1$
